cinderx.cpython-310-darwin.so
cinderx-0.0.1.dist-info/LICENSE
cinderx-0.0.1.dist-info/METADATA
cinderx-0.0.1.dist-info/WHEEL
cinderx-0.0.1.dist-info/top_level.txt
cinderx-0.0.1.dist-info/RECORD
