Metadata-Version: 2.1
Name: cinderx
Version: 0.0.1
Summary: High-performance Python runtime extensions
Home-page: https://github.com/facebookincubator/cinder
Author: Meta Platforms
Author-email: cinder@meta.com
Classifier: Development Status :: 1 - Planning
Classifier: Programming Language :: Python :: 3.12
Classifier: License :: OSI Approved :: MIT License
Classifier: Operating System :: OS Independent
Requires-Python: ==3.12.*
License-File: LICENSE
